py_plex_api/__init__.py
py_plex_api/py_plex_api.py
py_plex_api-0.2.0.dist-info/AUTHORS.rst
py_plex_api-0.2.0.dist-info/LICENSE
py_plex_api-0.2.0.dist-info/METADATA
py_plex_api-0.2.0.dist-info/WHEEL
py_plex_api-0.2.0.dist-info/entry_points.txt
py_plex_api-0.2.0.dist-info/top_level.txt
py_plex_api-0.2.0.dist-info/RECORD
