Metadata-Version: 2.1
Name: py-plex-api
Version: 0.2.0
Summary: API wrapper for interacting with a Plex Server
Home-page: https://github.com/paul-armstrong-dev/py_plex_api
Author: Paul Armstrong
Author-email: paul.armstrong211@gmail.com
License: MIT license
Keywords: py_plex_api
Platform: UNKNOWN
Classifier: Development Status :: 2 - Pre-Alpha
Classifier: Intended Audience :: Developers
Classifier: License :: OSI Approved :: MIT License
Classifier: Natural Language :: English
Classifier: Programming Language :: Python :: 3
Classifier: Programming Language :: Python :: 3.6
Classifier: Programming Language :: Python :: 3.7
Classifier: Programming Language :: Python :: 3.8
Requires-Python: >=3.6
License-File: LICENSE
License-File: AUTHORS.rst
Requires-Dist: loguru (==0.5.3)
Requires-Dist: requests (==2.25.1)
